philips_air_purifier_ac2889/__init__.py
philips_air_purifier_ac2889/_air_purifier.py
philips_air_purifier_ac2889/_utils.py
philips_air_purifier_ac2889/errors.py
philips_air_purifier_ac2889-2.0.0.dist-info/LICENSE.txt
philips_air_purifier_ac2889-2.0.0.dist-info/METADATA
philips_air_purifier_ac2889-2.0.0.dist-info/WHEEL
philips_air_purifier_ac2889-2.0.0.dist-info/top_level.txt
philips_air_purifier_ac2889-2.0.0.dist-info/RECORD
