Metadata-Version: 2.1
Name: philips-air-purifier-ac2889
Version: 2.0.0
Summary: A simple client to control the Philips AC2889 air purifier.
Author: marcinooo
License: The MIT License (MIT)
Project-URL: Homepage, https://github.com/marcinooo/philips-air-purifier
Project-URL: Issues, https://github.com/marcinooo/philips-air-purifier/issues
Classifier: Programming Language :: Python :: 3
Classifier: License :: OSI Approved :: MIT License
Requires-Python: >=3.6
License-File: LICENSE.txt
Requires-Dist: requests
Requires-Dist: pycryptodome
Requires-Dist: pycryptodomex
Provides-Extra: test
Requires-Dist: pylint ; extra == 'test'
Requires-Dist: pytest ; extra == 'test'
Requires-Dist: ddt ; extra == 'test'
